ttyp/__init__.py
ttyp/app.py
ttyp/args.py
ttyp/content.py
ttyp/main.py
ttyp/static/__init__.py
ttyp/static/languages/__init__.py
ttyp/static/languages/afrikaans.json
ttyp/static/languages/afrikaans_10k.json
ttyp/static/languages/afrikaans_1k.json
ttyp/static/languages/albanian.json
ttyp/static/languages/albanian_1k.json
ttyp/static/languages/amharic.json
ttyp/static/languages/amharic_1k.json
ttyp/static/languages/amharic_5k.json
ttyp/static/languages/arabic.json
ttyp/static/languages/arabic_10k.json
ttyp/static/languages/arabic_egypt.json
ttyp/static/languages/arabic_egypt_1k.json
ttyp/static/languages/armenian.json
ttyp/static/languages/armenian_1k.json
ttyp/static/languages/armenian_western.json
ttyp/static/languages/armenian_western_1k.json
ttyp/static/languages/azerbaijani.json
ttyp/static/languages/azerbaijani_1k.json
ttyp/static/languages/bangla.json
ttyp/static/languages/bangla_10k.json
ttyp/static/languages/bangla_letters.json
ttyp/static/languages/bashkir.json
ttyp/static/languages/belarusian.json
ttyp/static/languages/belarusian_100k.json
ttyp/static/languages/belarusian_10k.json
ttyp/static/languages/belarusian_1k.json
ttyp/static/languages/belarusian_25k.json
ttyp/static/languages/belarusian_50k.json
ttyp/static/languages/belarusian_5k.json
ttyp/static/languages/belarusian_lacinka.json
ttyp/static/languages/belarusian_lacinka_1k.json
ttyp/static/languages/bosnian.json
ttyp/static/languages/bosnian_4k.json
ttyp/static/languages/bulgarian.json
ttyp/static/languages/bulgarian_latin.json
ttyp/static/languages/catalan.json
ttyp/static/languages/catalan_1k.json
ttyp/static/languages/chinese_simplified.json
ttyp/static/languages/chinese_simplified_10k.json
ttyp/static/languages/chinese_simplified_1k.json
ttyp/static/languages/chinese_simplified_50k.json
ttyp/static/languages/chinese_simplified_5k.json
ttyp/static/languages/chinese_traditional.json
ttyp/static/languages/code_arduino.json
ttyp/static/languages/code_assembly.json
ttyp-0.1.8.dist-info/WHEEL
ttyp-0.1.8.dist-info/entry_points.txt
ttyp-0.1.8.dist-info/METADATA
ttyp-0.1.8.dist-info/RECORD
