Metadata-Version: 2.4
Name: ttyp
Version: 0.1.8
Summary: CLI typing test
Keywords: typing test,terminal,cli
Author: Felipe Jara
Author-email: Felipe Jara <fjararibet@gmail.com>
License-Expression: MIT
Requires-Dist: prompt-toolkit>=3.0.51
Requires-Python: >=3.10
Project-URL: Repository, https://github.com/fjararibet/ttyp
